setup.py
gisting/__init__.py
gisting.egg-info/PKG-INFO
gisting.egg-info/SOURCES.txt
gisting.egg-info/dependency_links.txt
gisting.egg-info/top_level.txt
gisting/src/__init__.py
gisting/src/arguments.py
gisting/src/benchmarking.py
gisting/src/compress.py
gisting/src/generation_utils.py
gisting/src/gist_caching.py
gisting/src/gist_llama.py
gisting/src/gist_t5.py
gisting/src/integrations.py
gisting/src/metrics.py
gisting/src/train.py
gisting/src/trainer_seq2seq.py
gisting/src/utils.py
gisting/src/weight_diff.py
gisting/src/data/__init__.py
gisting/src/data/gist.py
gisting/src/data/utils.py