Metadata-Version: 2.1
Name: gisting
Version: 1.3.6
Summary: A pip module for the Gisting Repo by Jesse Mu
Home-page: https://github.com/jayelm/gisting
Author: Owais Zahid
Author-email: owais.zahid@mail.utoronto.ca
License: UNKNOWN
Platform: UNKNOWN
Classifier: Development Status :: 4 - Beta
